README.md
setup.cfg
setup.py
flake8_functions_names/__init__.py
flake8_functions_names/checker.py
flake8_functions_names/custom_types.py
flake8_functions_names/validators.py
flake8_functions_names/words.py
flake8_functions_names.egg-info/PKG-INFO
flake8_functions_names.egg-info/SOURCES.txt
flake8_functions_names.egg-info/dependency_links.txt
flake8_functions_names.egg-info/entry_points.txt
flake8_functions_names.egg-info/not-zip-safe
flake8_functions_names.egg-info/requires.txt
flake8_functions_names.egg-info/top_level.txt
flake8_functions_names/utils/__init__.py
flake8_functions_names/utils/ast_parsers.py
flake8_functions_names/utils/imports.py