Metadata-Version: 2.1
Name: flake8-functions-names
Version: 0.0.5
Summary: An extension for flake8 that validates functions names, decomposition and conformity with annotations.
Home-page: https://github.com/Melevir/flake8-functions-names
Author: Ilya Lebedev
Author-email: melevir@gmail.com
License: MIT
Keywords: flake8
Platform: UNKNOWN
Classifier: Environment :: Console
Classifier: Framework :: Flake8
Classifier: Operating System :: OS Independent
Classifier: Topic :: Software Development :: Documentation
Classifier: Topic :: Software Development :: Libraries :: Python Modules
Classifier: Topic :: Software Development :: Quality Assurance
Classifier: Programming Language :: Python
Classifier: Programming Language :: Python :: 3.8
Classifier: Programming Language :: Python :: 3.9
Requires-Python: >=3.7
